{
 "cells": [
  {
   "cell_type": "code",
   "execution_count": 1,
   "metadata": {},
   "outputs": [
    {
     "name": "stdout",
     "output_type": "stream",
     "text": [
      "running register(<function f1 at 0x0000024C79DAD240>)\n",
      "running register(<function f2 at 0x0000024C79DAF010>)\n",
      "running main()\n",
      "registry -> [<function f1 at 0x0000024C79DAD240>, <function f2 at 0x0000024C79DAF010>]\n",
      "running f1()\n",
      "running f2()\n",
      "running f3()\n"
     ]
    }
   ],
   "source": [
    "# tag::REGISTRATION[]\n",
    "\n",
    "registry = []  # <1>\n",
    "\n",
    "def register(func):  # <2>\n",
    "    print(f'running register({func})')  # <3>\n",
    "    registry.append(func)  # <4>\n",
    "    return func  # <5>\n",
    "\n",
    "@register  # <6>\n",
    "def f1():\n",
    "    print('running f1()')\n",
    "\n",
    "@register\n",
    "def f2():\n",
    "    print('running f2()')\n",
    "\n",
    "def f3():  # <7>\n",
    "    print('running f3()')\n",
    "\n",
    "def main():  # <8>\n",
    "    print('running main()')\n",
    "    print('registry ->', registry)\n",
    "    f1()\n",
    "    f2()\n",
    "    f3()\n",
    "\n",
    "if __name__ == '__main__':\n",
    "    main()  # <9>\n",
    "\n",
    "# end::REGISTRATION[]\n"
   ]
  },
  {
   "cell_type": "code",
   "execution_count": 2,
   "metadata": {},
   "outputs": [
    {
     "name": "stdout",
     "output_type": "stream",
     "text": [
      "3\n"
     ]
    },
    {
     "ename": "NameError",
     "evalue": "name 'b' is not defined",
     "output_type": "error",
     "traceback": [
      "\u001b[1;31m---------------------------------------------------------------------------\u001b[0m",
      "\u001b[1;31mNameError\u001b[0m                                 Traceback (most recent call last)",
      "\u001b[1;32md:\\workspaces\\example-code-2e\\09-closure-deco\\09-closure-deco.ipynb Cell 2\u001b[0m in \u001b[0;36m<cell line: 5>\u001b[1;34m()\u001b[0m\n\u001b[0;32m      <a href='vscode-notebook-cell:/d%3A/workspaces/example-code-2e/09-closure-deco/09-closure-deco.ipynb#W1sZmlsZQ%3D%3D?line=1'>2</a>\u001b[0m     \u001b[39mprint\u001b[39m(a)\n\u001b[0;32m      <a href='vscode-notebook-cell:/d%3A/workspaces/example-code-2e/09-closure-deco/09-closure-deco.ipynb#W1sZmlsZQ%3D%3D?line=2'>3</a>\u001b[0m     \u001b[39mprint\u001b[39m(b)\n\u001b[1;32m----> <a href='vscode-notebook-cell:/d%3A/workspaces/example-code-2e/09-closure-deco/09-closure-deco.ipynb#W1sZmlsZQ%3D%3D?line=4'>5</a>\u001b[0m f1(\u001b[39m3\u001b[39;49m)\n",
      "\u001b[1;32md:\\workspaces\\example-code-2e\\09-closure-deco\\09-closure-deco.ipynb Cell 2\u001b[0m in \u001b[0;36mf1\u001b[1;34m(a)\u001b[0m\n\u001b[0;32m      <a href='vscode-notebook-cell:/d%3A/workspaces/example-code-2e/09-closure-deco/09-closure-deco.ipynb#W1sZmlsZQ%3D%3D?line=0'>1</a>\u001b[0m \u001b[39mdef\u001b[39;00m \u001b[39mf1\u001b[39m(a):\n\u001b[0;32m      <a href='vscode-notebook-cell:/d%3A/workspaces/example-code-2e/09-closure-deco/09-closure-deco.ipynb#W1sZmlsZQ%3D%3D?line=1'>2</a>\u001b[0m     \u001b[39mprint\u001b[39m(a)\n\u001b[1;32m----> <a href='vscode-notebook-cell:/d%3A/workspaces/example-code-2e/09-closure-deco/09-closure-deco.ipynb#W1sZmlsZQ%3D%3D?line=2'>3</a>\u001b[0m     \u001b[39mprint\u001b[39m(b)\n",
      "\u001b[1;31mNameError\u001b[0m: name 'b' is not defined"
     ]
    }
   ],
   "source": [
    "def f1(a):\n",
    "    print(a)\n",
    "    print(b)\n",
    "    \n",
    "f1(3)"
   ]
  },
  {
   "cell_type": "code",
   "execution_count": null,
   "metadata": {},
   "outputs": [
    {
     "name": "stdout",
     "output_type": "stream",
     "text": [
      "  2           0 LOAD_GLOBAL              0 (print)\n",
      "              2 LOAD_FAST                0 (a)\n",
      "              4 CALL_FUNCTION            1\n",
      "              6 POP_TOP\n",
      "\n",
      "  3           8 LOAD_GLOBAL              0 (print)\n",
      "             10 LOAD_GLOBAL              1 (b)\n",
      "             12 CALL_FUNCTION            1\n",
      "             14 POP_TOP\n",
      "             16 LOAD_CONST               0 (None)\n",
      "             18 RETURN_VALUE\n"
     ]
    }
   ],
   "source": [
    "from dis import dis\n",
    "dis(f1)"
   ]
  },
  {
   "cell_type": "code",
   "execution_count": null,
   "metadata": {},
   "outputs": [
    {
     "name": "stdout",
     "output_type": "stream",
     "text": [
      "2152394195248\n",
      "2152394195248\n",
      "2152394198320\n",
      "99\n",
      "6\n"
     ]
    }
   ],
   "source": [
    "b = 6\n",
    "def f2(a):\n",
    "    print(id(a))\n",
    "    a = 99\n",
    "    print(id(a))    \n",
    "    print(a)\n",
    "    print(b)    \n",
    "\n",
    "\n",
    "c = 3\n",
    "print(id(c))    \n",
    "f2(c)"
   ]
  },
  {
   "cell_type": "code",
   "execution_count": null,
   "metadata": {},
   "outputs": [
    {
     "name": "stdout",
     "output_type": "stream",
     "text": [
      "  3           0 LOAD_GLOBAL              0 (print)\n",
      "              2 LOAD_FAST                0 (a)\n",
      "              4 CALL_FUNCTION            1\n",
      "              6 POP_TOP\n",
      "\n",
      "  4           8 LOAD_GLOBAL              0 (print)\n",
      "             10 LOAD_FAST                1 (b)\n",
      "             12 CALL_FUNCTION            1\n",
      "             14 POP_TOP\n",
      "\n",
      "  5          16 LOAD_CONST               1 (9)\n",
      "             18 STORE_FAST               1 (b)\n",
      "             20 LOAD_CONST               0 (None)\n",
      "             22 RETURN_VALUE\n"
     ]
    }
   ],
   "source": [
    "from dis import dis\n",
    "dis(f2)"
   ]
  },
  {
   "cell_type": "markdown",
   "metadata": {},
   "source": [
    "## Disassemble statements that are not inside a function"
   ]
  },
  {
   "cell_type": "code",
   "execution_count": null,
   "metadata": {},
   "outputs": [
    {
     "name": "stdout",
     "output_type": "stream",
     "text": [
      "  2           0 LOAD_CONST               0 (6)\n",
      "              2 STORE_NAME               0 (b)\n",
      "\n",
      "  3           4 LOAD_CONST               1 (<code object f2 at 0x000001F52B0F0660, file \"<dis>\", line 3>)\n",
      "              6 LOAD_CONST               2 ('f2')\n",
      "              8 MAKE_FUNCTION            0\n",
      "             10 STORE_NAME               1 (f2)\n",
      "\n",
      "  8          12 LOAD_CONST               3 (20)\n",
      "             14 STORE_NAME               2 (c)\n",
      "\n",
      "  9          16 LOAD_NAME                1 (f2)\n",
      "             18 LOAD_NAME                2 (c)\n",
      "             20 CALL_FUNCTION            1\n",
      "             22 POP_TOP\n",
      "             24 LOAD_CONST               4 (None)\n",
      "             26 RETURN_VALUE\n",
      "\n",
      "Disassembly of <code object f2 at 0x000001F52B0F0660, file \"<dis>\", line 3>:\n",
      "  4           0 LOAD_GLOBAL              0 (print)\n",
      "              2 LOAD_FAST                0 (a)\n",
      "              4 CALL_FUNCTION            1\n",
      "              6 POP_TOP\n",
      "\n",
      "  5           8 LOAD_GLOBAL              0 (print)\n",
      "             10 LOAD_FAST                1 (b)\n",
      "             12 CALL_FUNCTION            1\n",
      "             14 POP_TOP\n",
      "\n",
      "  6          16 LOAD_CONST               1 (9)\n",
      "             18 STORE_FAST               1 (b)\n",
      "             20 LOAD_CONST               0 (None)\n",
      "             22 RETURN_VALUE\n"
     ]
    }
   ],
   "source": [
    "import dis\n",
    "\n",
    "code = \"\"\"\n",
    "b = 6\n",
    "def f2(a):\n",
    "    print(a)\n",
    "    print(b)    \n",
    "    b = 9\n",
    "\n",
    "c = 20\n",
    "f2(c)\n",
    "\"\"\"\n",
    "\n",
    "dis.dis(code)"
   ]
  },
  {
   "cell_type": "code",
   "execution_count": null,
   "metadata": {},
   "outputs": [
    {
     "name": "stdout",
     "output_type": "stream",
     "text": [
      "  2           0 LOAD_CONST               0 (10)\n",
      "              2 STORE_NAME               0 (a)\n",
      "\n",
      "  3           4 LOAD_CONST               1 (20)\n",
      "              6 STORE_NAME               1 (b)\n",
      "\n",
      "  4           8 LOAD_NAME                0 (a)\n",
      "             10 LOAD_NAME                1 (b)\n",
      "             12 BINARY_ADD\n",
      "             14 STORE_NAME               2 (result)\n",
      "\n",
      "  5          16 LOAD_NAME                3 (print)\n",
      "             18 LOAD_NAME                2 (result)\n",
      "             20 CALL_FUNCTION            1\n",
      "             22 POP_TOP\n",
      "             24 LOAD_CONST               2 (None)\n",
      "             26 RETURN_VALUE\n"
     ]
    }
   ],
   "source": [
    "import dis\n",
    "\n",
    "code_obj = compile(\"\"\"\n",
    "a = 10\n",
    "b = 20\n",
    "result = a + b\n",
    "print(result)\n",
    "\"\"\", \"<string>\", \"exec\")\n",
    "\n",
    "dis.dis(code_obj)"
   ]
  },
  {
   "cell_type": "markdown",
   "metadata": {},
   "source": [
    "## Closures"
   ]
  },
  {
   "cell_type": "code",
   "execution_count": 1,
   "metadata": {},
   "outputs": [
    {
     "data": {
      "text/plain": [
       "11.0"
      ]
     },
     "execution_count": 1,
     "metadata": {},
     "output_type": "execute_result"
    }
   ],
   "source": [
    "from average_oo import Averager\n",
    "\n",
    "avg = Averager()\n",
    "avg(10)\n",
    "avg(11)\n",
    "avg(12)"
   ]
  },
  {
   "cell_type": "code",
   "execution_count": 12,
   "metadata": {},
   "outputs": [
    {
     "data": {
      "text/plain": [
       "11.0"
      ]
     },
     "execution_count": 12,
     "metadata": {},
     "output_type": "execute_result"
    }
   ],
   "source": [
    "from average import make_averager\n",
    "\n",
    "avg = make_averager()\n",
    "avg(10)\n",
    "avg(11)\n",
    "avg(12)"
   ]
  },
  {
   "cell_type": "code",
   "execution_count": 13,
   "metadata": {},
   "outputs": [
    {
     "data": {
      "text/plain": [
       "30.0"
      ]
     },
     "execution_count": 13,
     "metadata": {},
     "output_type": "execute_result"
    }
   ],
   "source": [
    "avg1 = make_averager()\n",
    "avg1(20)\n",
    "avg1(30)\n",
    "avg1(40)"
   ]
  },
  {
   "cell_type": "code",
   "execution_count": 4,
   "metadata": {},
   "outputs": [
    {
     "data": {
      "text/plain": [
       "('new_value', 'total')"
      ]
     },
     "execution_count": 4,
     "metadata": {},
     "output_type": "execute_result"
    }
   ],
   "source": [
    "avg.__code__.co_varnames"
   ]
  },
  {
   "cell_type": "code",
   "execution_count": 6,
   "metadata": {},
   "outputs": [
    {
     "data": {
      "text/plain": [
       "('series',)"
      ]
     },
     "execution_count": 6,
     "metadata": {},
     "output_type": "execute_result"
    }
   ],
   "source": [
    "avg.__code__.co_freevars"
   ]
  },
  {
   "cell_type": "code",
   "execution_count": 8,
   "metadata": {},
   "outputs": [
    {
     "data": {
      "text/plain": [
       "(<cell at 0x000002633EFD1720: list object at 0x000002633F015300>,)"
      ]
     },
     "execution_count": 8,
     "metadata": {},
     "output_type": "execute_result"
    }
   ],
   "source": [
    "avg.__closure__"
   ]
  },
  {
   "cell_type": "code",
   "execution_count": 9,
   "metadata": {},
   "outputs": [
    {
     "data": {
      "text/plain": [
       "(<cell at 0x000002633EFD2410: list object at 0x000002633F015CC0>,)"
      ]
     },
     "execution_count": 9,
     "metadata": {},
     "output_type": "execute_result"
    }
   ],
   "source": [
    "avg1.__closure__"
   ]
  },
  {
   "cell_type": "code",
   "execution_count": 10,
   "metadata": {},
   "outputs": [
    {
     "data": {
      "text/plain": [
       "[10, 11, 12]"
      ]
     },
     "execution_count": 10,
     "metadata": {},
     "output_type": "execute_result"
    }
   ],
   "source": [
    "avg.__closure__[0].cell_contents"
   ]
  },
  {
   "cell_type": "code",
   "execution_count": 11,
   "metadata": {},
   "outputs": [
    {
     "data": {
      "text/plain": [
       "[20, 30, 40]"
      ]
     },
     "execution_count": 11,
     "metadata": {},
     "output_type": "execute_result"
    }
   ],
   "source": [
    "avg1.__closure__[0].cell_contents"
   ]
  },
  {
   "cell_type": "markdown",
   "metadata": {},
   "source": [
    "## The nonlocal Declaration"
   ]
  },
  {
   "cell_type": "code",
   "execution_count": null,
   "metadata": {},
   "outputs": [],
   "source": [
    "def make_averager():\n",
    "    count = 0\n",
    "    total = 0\n",
    "    \n",
    "    def averager(new_value):\n",
    "        nonlocal count, total\n",
    "        count += 1\n",
    "        total += new_value\n",
    "        return total / count\n",
    "    \n",
    "    return averager"
   ]
  },
  {
   "cell_type": "code",
   "execution_count": null,
   "metadata": {},
   "outputs": [
    {
     "data": {
      "text/plain": [
       "11.0"
      ]
     },
     "execution_count": 3,
     "metadata": {},
     "output_type": "execute_result"
    }
   ],
   "source": [
    "avg = make_averager()\n",
    "avg(10)\n",
    "avg(11)\n",
    "avg(12)"
   ]
  },
  {
   "cell_type": "code",
   "execution_count": null,
   "metadata": {},
   "outputs": [
    {
     "data": {
      "text/plain": [
       "('new_value',)"
      ]
     },
     "execution_count": 4,
     "metadata": {},
     "output_type": "execute_result"
    }
   ],
   "source": [
    "avg.__code__.co_varnames"
   ]
  },
  {
   "cell_type": "code",
   "execution_count": null,
   "metadata": {},
   "outputs": [
    {
     "data": {
      "text/plain": [
       "('count', 'total')"
      ]
     },
     "execution_count": 5,
     "metadata": {},
     "output_type": "execute_result"
    }
   ],
   "source": [
    "avg.__code__.co_freevars"
   ]
  },
  {
   "cell_type": "code",
   "execution_count": null,
   "metadata": {},
   "outputs": [
    {
     "data": {
      "text/plain": [
       "(<cell at 0x000002339F7F2EC0: int object at 0x000002339ADE0130>,\n",
       " <cell at 0x000002339F7F3DC0: int object at 0x000002339ADE04F0>)"
      ]
     },
     "execution_count": 6,
     "metadata": {},
     "output_type": "execute_result"
    }
   ],
   "source": [
    "avg.__closure__"
   ]
  },
  {
   "cell_type": "code",
   "execution_count": null,
   "metadata": {},
   "outputs": [
    {
     "data": {
      "text/plain": [
       "3"
      ]
     },
     "execution_count": 10,
     "metadata": {},
     "output_type": "execute_result"
    }
   ],
   "source": [
    "avg.__closure__[0].cell_contents"
   ]
  },
  {
   "cell_type": "code",
   "execution_count": null,
   "metadata": {},
   "outputs": [
    {
     "data": {
      "text/plain": [
       "33"
      ]
     },
     "execution_count": 11,
     "metadata": {},
     "output_type": "execute_result"
    }
   ],
   "source": [
    "avg.__closure__[1].cell_contents"
   ]
  }
 ],
 "metadata": {
  "kernelspec": {
   "display_name": "Python 3",
   "language": "python",
   "name": "python3"
  },
  "language_info": {
   "codemirror_mode": {
    "name": "ipython",
    "version": 3
   },
   "file_extension": ".py",
   "mimetype": "text/x-python",
   "name": "python",
   "nbconvert_exporter": "python",
   "pygments_lexer": "ipython3",
   "version": "3.10.6"
  },
  "orig_nbformat": 4
 },
 "nbformat": 4,
 "nbformat_minor": 2
}
